madato-0.7.1.dist-info/METADATA
madato-0.7.1.dist-info/WHEEL
madato-0.7.1.dist-info/licenses/LICENSE
madato-0.7.1.dist-info/licenses/LICENSE-APACHE
madato-0.7.1.dist-info/licenses/LICENSE-MIT
madato/__init__.py
madato/madato.pypy311-pp73-arm-linux-gnu.so
madato/py.typed
madato-0.7.1.dist-info/RECORD
