Metadata-Version: 2.4
Name: madato
Version: 0.7.1
Classifier: Development Status :: 5 - Production/Stable
Classifier: Programming Language :: Python
Classifier: Programming Language :: Python :: 3
Classifier: Programming Language :: Python :: 3 :: Only
Classifier: Programming Language :: Python :: 3.8
Classifier: Programming Language :: Python :: 3.9
Classifier: Programming Language :: Python :: 3.10
Classifier: Programming Language :: Python :: 3.11
Classifier: Programming Language :: Python :: 3.12
Classifier: License :: OSI Approved :: MIT License
Classifier: License :: OSI Approved :: Apache Software License
Classifier: Operating System :: POSIX :: Linux
Classifier: Operating System :: Microsoft :: Windows
Classifier: Operating System :: MacOS
Classifier: Topic :: Software Development :: Libraries :: Python Modules
Classifier: Topic :: Text Processing :: Markup
Classifier: Topic :: Text Processing :: Markup :: Markdown
Requires-Dist: maturin>=1.5 ; extra == 'dev'
Requires-Dist: pyyaml>=6 ; extra == 'dev'
Requires-Dist: pytest>=7.3 ; extra == 'dev'
Requires-Dist: ipykernel>=6 ; extra == 'dev'
Provides-Extra: dev
License-File: LICENSE
License-File: LICENSE-APACHE
License-File: LICENSE-MIT
Summary: Convert between various formats (YAML, JSON, XLSX, ODS, CSV) to Markdown Tables
Author-email: Ramon Buckland <ramon@thebuckland.com>
License: MIT License
Requires-Python: >=3.7
Project-URL: Homepage, https://github.com/inosion/madato
Project-URL: Funding, https://github.com/sponsors/inosion
Project-URL: Source, https://github.com/inosion/madato
Project-URL: Changelog, https://github.com/inosion/madato/releases
